squrt_math/__init__.py
squrt_math/module1.py
squrt_math-0.1.0.dist-info/METADATA
squrt_math-0.1.0.dist-info/WHEEL
squrt_math-0.1.0.dist-info/licence1
squrt_math-0.1.0.dist-info/top_level.txt
squrt_math-0.1.0.dist-info/RECORD
